insightspy/ComparisonsMixin.py
insightspy/PipelinesMixin.py
insightspy/PortalSession.py
insightspy/ProjectsMixin.py
insightspy/ReferenceSetMixin.py
insightspy/SamplesMixin.py
insightspy/SessionCore.py
insightspy/SignaturesMixin.py
insightspy/__init__.py
insightspy/__version__.py
insightspy/utils.py
insightspy-0.0.8.dist-info/METADATA
insightspy-0.0.8.dist-info/WHEEL
insightspy-0.0.8.dist-info/top_level.txt
insightspy-0.0.8.dist-info/RECORD
