Metadata-Version: 2.1
Name: insightspy
Version: 0.0.8
Summary: Python API for Arpeggio Biosciences data portal
Home-page: https://github.com/ArpeggioBiosciences/insightspy
Author: Noah Dukler
Author-email: noah@arpeggiobio.com
License: UNKNOWN
Platform: UNKNOWN
Classifier: Programming Language :: Python :: 3
Classifier: Operating System :: OS Independent
Requires-Python: >=3.7.*
Requires-Dist: pandas
Requires-Dist: tqdm
Requires-Dist: requests
